yamlc/__init__.py
yamlc/yamlc.py
yamlc-0.1.10.dist-info/LICENSE
yamlc-0.1.10.dist-info/METADATA
yamlc-0.1.10.dist-info/WHEEL
yamlc-0.1.10.dist-info/top_level.txt
yamlc-0.1.10.dist-info/RECORD
