Metadata-Version: 2.1
Name: yamlc
Version: 0.1.10
Summary: A simple YAML configuration loader
Home-page: https://github.com/hongenge/yamlc
Author: 陌北v1
Author-email: hongen.me@gmail.com
License: MIT
Classifier: Programming Language :: Python :: 3
Classifier: License :: OSI Approved :: MIT License
Classifier: Operating System :: OS Independent
Requires-Python: >=3.6
License-File: LICENSE
Requires-Dist: pyyaml
